{
  "plugin.title": "JellyTrack",
  "plugin.description": "Sendet Wiedergabeereignisse und Metadaten an JellyTrack zur Analyse.",
  "config.enable": "Plugin aktivieren",
  "config.jellytrackUrl.label": "JellyTrack-URL",
  "config.jellytrackUrl.description": "Ziel-URL. Beispiele: http://192.168.1.100:3000/api/plugin/events",
  "config.apiKey.label": "API-Schlüssel",
  "config.apiKey.placeholder": "jt_xxxxxxxxxxxx",
  "config.heartbeatInterval.label": "Intervall des Lebenszeichens (Sekunden)",
  "config.heartbeatInterval.description": "Intervall zwischen Heartbeats an JellyTrack (Standard: 600 Sekunden)",
  "config.progressInterval.label": "Intervall für die Aktualisierung des Wiedergabefortschritts (Sekunden)",
  "config.progressInterval.description": "Intervall waehrend aktiver Wiedergabe (Standard: 5 Sekunden)",
  "config.preferredLanguage.label": "Bevorzugte Sprache (optional)",
  "config.preferredLanguage.description": "Wählen Sie die Sprache für JellyTrack. 'Auto' verwendet die Sprache des Jellyfin-Servers.",
  "config.testConnection": "Verbindung testen",
  "config.test.connection.success": "Verbindung erfolgreich zu {endpoint}",
  "config.test.connection.success.simple": "Verbindung erfolgreich!",
  "config.test.connection.error": "Fehler: {message}",
  "config.save": "Speichern",
  "config.show": "Anzeigen",
  "config.hide": "Ausblenden",
  "config.test.inProgress": "Teste...",
  "config.apiKey.description": "Der in den JellyTrack-Einstellungen generierte API-Schlüssel (Format: jt_xxxxxxxxxxxx)",
  "config.fillFields": "Bitte sowohl die URL als auch den API-Schlüssel ausfüllen.",
  "config.pausedProgressInterval.label": "Pauseintervall (Sekunden)",
  "config.pausedProgressInterval.description": "Intervall waehrend pausierter Wiedergabe (Standard: 30 Sekunden)",
  "config.seekThreshold.label": "Manual jump threshold (seconds)",
  "config.seekThreshold.description": "Minimum position jump reported as a manual skip or rewind (default: 20 seconds)",
  "config.retryQueueSize.label": "Maximale Retry-Warteschlange",
  "config.retryQueueSize.description": "Maximale lokal gespeicherte Ereignisse, wenn JellyTrack nicht verfuegbar ist (Standard: 500)",
  "config.retryFlushBatchSize.label": "Retry-Flush-Batchgroesse",
  "config.retryFlushBatchSize.description": "Maximale Ereignisse pro Flush, wenn JellyTrack wieder antwortet (Standard: 50)",
  "config.trackPauseResume": "Pause und Fortsetzen sofort erfassen",
  "config.trackSeek": "Capture manual skips and rewinds immediately",
  "config.trackAudioSubtitleChanges": "Audio- und Untertitelwechsel erfassen",
  "config.trackSessionEnded": "Wiedergaben schliessen, wenn eine Sitzung endet",
  "config.preferredLanguage.auto": "Auto - Sprache des Jellyfin-Servers verwenden",
  "task.heartbeat.name": "JellyTrack-Lebenszeichen",
  "task.heartbeat.description": "Sends a periodic heartbeat to JellyTrack with user and plugin health information."
}
